auth/__init__.py
auth/login.py
auth/logout.py
cli/__init__.py
download_bids/__init__.py
download_bids/main.py
download_bids/xnat2bids.py
download_dicom/__init__.py
download_dicom/main.py
upload_bids/__init__.py
upload_bids/main.py
upload_bids/utilities/__init__.py
upload_bids/utilities/core.py
upload_bids/utilities/experiments.py
upload_bids/utilities/fileServices.py
upload_bids/utilities/scan.py
upload_bids/utilities/schema.py
upload_bids/utilities/signals.py
upload_dicom/__init__.py
upload_dicom/main.py
utilities/__init__.py
utilities/check_config.py
xnat_cli_tool-1.0.13.dist-info/METADATA
xnat_cli_tool-1.0.13.dist-info/WHEEL
xnat_cli_tool-1.0.13.dist-info/entry_points.txt
xnat_cli_tool-1.0.13.dist-info/top_level.txt
xnat_cli_tool-1.0.13.dist-info/RECORD
